{
  "name": "Story 01",
  "minimum-level": 10,
  "default-map" : "map02",
  "maps": [
    "map02.json",
    "map01.json",
    "maison01.json",
    "inside.json",
    "MainTown.json"
  ],
  "weapons": [
    "weapon01.json"
  ],
  "bullets": [
    "bullet01.json"
  ],
  "mobs": [
    "mob01.json"
  ],
  "sounds": {
    "RUN": {
      "type": "effect",
      "src": "sound01.mp3"
    },
    "ENTER_ZONE": {
      "type": "music",
      "src": "sound02.mp3"
    }
  },
  "zones": {
    "ZONE1": {
      "attacks": [
        {
          "mob": "mob01",
          "force": 1,
          "count": 1
        }
      ],
      "items": [
        {
          "type": "border-left",
          "rotate": 0,
          "item": "fence"
        }
      ],
      "sounds": ["ENTER_ZONE"],
      "max-enter": -1,
      "max-execute": -1,
      "general": true,
      "blocked": false,
      "max-revive": 2,
      "time-in": 600,
      "gates": {
        "PM1": {"opened": true}
      }
    },
    "ZONE2": {

    }
  },
  "gates": {

  }
}